update_repo
