Metadata-Version: 2.1
Name: update-repo
Version: 0.0.4
Summary: clone/pull a repo
Home-page: http://github.com/ffreemt/update-repo
Author: mikeee
License: MIT License
Download-URL: https://github.com/ffreemt/update-repo/archive/v_0.0.4.tar.gz
Keywords: git,colab
Platform: UNKNOWN
Classifier: Development Status :: 3 - Alpha
Classifier: Intended Audience :: Developers
Classifier: Programming Language :: Python :: 3
Classifier: Programming Language :: Python :: 3.5
Classifier: Programming Language :: Python :: 3.6
Classifier: License :: OSI Approved :: MIT License
